LICENSE
MANIFEST.in
README.md
setup.py
keeper_secrets_manager_helper/__init__.py
keeper_secrets_manager_helper/common.py
keeper_secrets_manager_helper/exception.py
keeper_secrets_manager_helper/field.py
keeper_secrets_manager_helper/field_type.py
keeper_secrets_manager_helper/format.py
keeper_secrets_manager_helper/record.py
keeper_secrets_manager_helper/record_type.py
keeper_secrets_manager_helper.egg-info/PKG-INFO
keeper_secrets_manager_helper.egg-info/SOURCES.txt
keeper_secrets_manager_helper.egg-info/dependency_links.txt
keeper_secrets_manager_helper.egg-info/not-zip-safe
keeper_secrets_manager_helper.egg-info/requires.txt
keeper_secrets_manager_helper.egg-info/top_level.txt
keeper_secrets_manager_helper/v3/__init__.py
keeper_secrets_manager_helper/v3/default_record_types.yml
keeper_secrets_manager_helper/v3/enum.py
keeper_secrets_manager_helper/v3/field_type.py
keeper_secrets_manager_helper/v3/parser.py
keeper_secrets_manager_helper/v3/record.py
keeper_secrets_manager_helper/v3/record_type.py