Metadata-Version: 2.4
Name: keeper-secrets-manager-helper
Version: 1.0.7
Summary: Keeper Secrets Manager SDK helper for managing records.
Home-page: https://github.com/Keeper-Security/secrets-manager
Author: Keeper Security
Author-email: sm@keepersecurity.com
License: MIT
Project-URL: Bug Tracker, https://github.com/Keeper-Security/secrets-manager/issues
Project-URL: Documentation, https://app.gitbook.com/@keeper-security/s/secrets-manager/secrets-manager
Project-URL: Source Code, https://github.com/Keeper-Security/secrets-manager
Keywords: Keeper Password Secrets Manager Helper Record
Classifier: Development Status :: 1 - Planning
Classifier: Intended Audience :: Developers
Classifier: License :: OSI Approved :: MIT License
Classifier: Operating System :: OS Independent
Classifier: Programming Language :: Python
Classifier: Programming Language :: Python :: 3
Classifier: Programming Language :: Python :: 3.6
Classifier: Programming Language :: Python :: 3.7
Classifier: Programming Language :: Python :: 3.8
Classifier: Programming Language :: Python :: 3.9
Classifier: Programming Language :: Python :: 3.10
Classifier: Programming Language :: Python :: 3.11
Classifier: Programming Language :: Python :: 3.12
Classifier: Programming Language :: Python :: 3.13
Classifier: Topic :: Security
Requires-Python: >=3.6
License-File: LICENSE
Requires-Dist: keeper-secrets-manager-core>=17.1.0
Requires-Dist: pyyaml>=6.0.1
Requires-Dist: iso8601
Dynamic: author
Dynamic: author-email
Dynamic: classifier
Dynamic: description
Dynamic: description-content-type
Dynamic: home-page
Dynamic: keywords
Dynamic: license
Dynamic: license-file
Dynamic: project-url
Dynamic: requires-dist
Dynamic: requires-python
Dynamic: summary
